README.md
setup.py
pdc/__init__.py
pdc/settings.py
pdc/helpers/__init__.py
pdc/helpers/login/Tuser.py
pdc/helpers/login/__init__.py
pdc/helpers/login/auth.py
pdc_dev.egg-info/PKG-INFO
pdc_dev.egg-info/SOURCES.txt
pdc_dev.egg-info/dependency_links.txt
pdc_dev.egg-info/requires.txt
pdc_dev.egg-info/top_level.txt