Metadata-Version: 1.0
Name: pdc-dev
Version: 0.2.6
Summary: library with pdc funcionalities
Home-page: https://github.com/Personal-Data-Center/pdc_dev
Author: Lucas Coraça Silva
Author-email: UNKNOWN
License: GPL
Platform: UNKNOWN
